tracing_lib/__init__.py
tracing_lib/tracing.py
tracing_lib/tracing_auto_link_parent.py
TracingLib-0.4.dist-info/LICENSE
TracingLib-0.4.dist-info/METADATA
TracingLib-0.4.dist-info/WHEEL
TracingLib-0.4.dist-info/top_level.txt
TracingLib-0.4.dist-info/RECORD
